louie/__init__.py
louie/dispatcher.py
louie/error.py
louie/plugin.py
louie/robustapply.py
louie/saferef.py
louie/sender.py
louie/signal.py
louie/version.py
louie/test/__init__.py
louie/test/conftest.py
louie/test/fixture.py
louie/test/test_dispatcher.py
louie/test/test_plugin.py
louie/test/test_robustapply.py
louie/test/test_saferef.py
Louie-2.0.1.dist-info/METADATA
Louie-2.0.1.dist-info/WHEEL
Louie-2.0.1.dist-info/top_level.txt
Louie-2.0.1.dist-info/RECORD
