Metadata-Version: 2.1
Name: Louie
Version: 2.0.1
Summary: Signal dispatching mechanism
Home-page: https://github.com/11craft/louie/
Download-URL: https://pypi.python.org/pypi/Louie
Author: Patrick K. O'Brien and contributors
License: BSD
Classifier: Intended Audience :: Developers
Classifier: License :: OSI Approved :: BSD License
Classifier: Programming Language :: Python
Classifier: Topic :: Software Development :: Libraries :: Python Modules
Requires-Python: >=3.6
